[
  {
    "Campaign": "ULHT_Licenciaturas",
    "Status": "ENABLED",
    "Budget": 208.0,
    "Impressions": 53965.0,
    "Clicks": 3456.0,
    "Cost": 4270.57095,
    "Conversions": 48.4,
    "CTR": "0,06404",
    "CostPerConv": 88.23493698
  },
  {
    "Campaign": "ULHT_Geral",
    "Status": "ENABLED",
    "Budget": 41.0,
    "Impressions": 20738.0,
    "Clicks": 9470.0,
    "Cost": 681.624885,
    "Conversions": 147.0,
    "CTR": "0,45665",
    "CostPerConv": 4.63690398
  },
  {
    "Campaign": "ULHT_Doutoramentos",
    "Status": "ENABLED",
    "Budget": 25.0,
    "Impressions": 2907.0,
    "Clicks": 216.0,
    "Cost": 396.681396,
    "Conversions": 0.0,
    "CTR": "0,0743",
    "CostPerConv": 0.0
  },
  {
    "Campaign": "ULHT_Mestrados",
    "Status": "ENABLED",
    "Budget": 125.0,
    "Impressions": 16561.0,
    "Clicks": 1805.0,
    "Cost": 2045.457451,
    "Conversions": 11.6,
    "CTR": "0,10899",
    "CostPerConv": 176.3325389
  },
  {
    "Campaign": "ULP_Licenciaturas_Search",
    "Status": "ENABLED",
    "Budget": 83.0,
    "Impressions": 15311.0,
    "Clicks": 1320.0,
    "Cost": 1352.369315,
    "Conversions": 6.4567,
    "CTR": "0,08621",
    "CostPerConv": 209.4520909
  },
  {
    "Campaign": "ULP_Mestrados_Search",
    "Status": "ENABLED",
    "Budget": 58.0,
    "Impressions": 4921.0,
    "Clicks": 339.0,
    "Cost": 948.252722,
    "Conversions": 6.0,
    "CTR": "0,06889",
    "CostPerConv": 158.0421203
  },
  {
    "Campaign": "ULP_Doutoramentos_Search",
    "Status": "ENABLED",
    "Budget": 20.0,
    "Impressions": 429.0,
    "Clicks": 27.0,
    "Cost": 77.048701,
    "Conversions": 2.0,
    "CTR": "0,06294",
    "CostPerConv": 38.5243505
  },
  {
    "Campaign": "ULHT_Display_Áreas_Remarketing",
    "Status": "PAUSED",
    "Budget": 11.0,
    "Impressions": 0.0,
    "Clicks": 0.0,
    "Cost": 0.0,
    "Conversions": 0.0,
    "CTR": "0",
    "CostPerConv": 0.0
  },
  {
    "Campaign": "ULP_Remarketing_Display",
    "Status": "PAUSED",
    "Budget": 11.0,
    "Impressions": 0.0,
    "Clicks": 0.0,
    "Cost": 0.0,
    "Conversions": 0.0,
    "CTR": "0",
    "CostPerConv": 0.0
  },
  {
    "Campaign": "ULHT_Brasil_Licenciaturas",
    "Status": "PAUSED",
    "Budget": 42.0,
    "Impressions": 0.0,
    "Clicks": 0.0,
    "Cost": 0.0,
    "Conversions": 0.0,
    "CTR": "0",
    "CostPerConv": 0.0
  },
  {
    "Campaign": "ULHT_PG's",
    "Status": "PAUSED",
    "Budget": 11.0,
    "Impressions": 0.0,
    "Clicks": 0.0,
    "Cost": 0.0,
    "Conversions": 0.0,
    "CTR": "0",
    "CostPerConv": 0.0
  },
  {
    "Campaign": "ULP_Geral Institucional_Search",
    "Status": "ENABLED",
    "Budget": 41.0,
    "Impressions": 13731.0,
    "Clicks": 3508.0,
    "Cost": 664.088791,
    "Conversions": 19.5433,
    "CTR": "0,25548",
    "CostPerConv": 33.98038156
  },
  {
    "Campaign": "ULHT_Display_Áreas",
    "Status": "PAUSED",
    "Budget": 22.0,
    "Impressions": 0.0,
    "Clicks": 0.0,
    "Cost": 0.0,
    "Conversions": 0.0,
    "CTR": "0",
    "CostPerConv": 0.0
  },
  {
    "Campaign": "ULP_Campanha_Display",
    "Status": "PAUSED",
    "Budget": 11.0,
    "Impressions": 0.0,
    "Clicks": 0.0,
    "Cost": 0.0,
    "Conversions": 0.0,
    "CTR": "0",
    "CostPerConv": 0.0
  },
  {
    "Campaign": "ULHT_Formações_Modulares",
    "Status": "PAUSED",
    "Budget": 28.0,
    "Impressions": 0.0,
    "Clicks": 0.0,
    "Cost": 0.0,
    "Conversions": 0.0,
    "CTR": "0",
    "CostPerConv": 0.0
  },
  {
    "Campaign": "ULHT_Display_PGs",
    "Status": "PAUSED",
    "Budget": 7.0,
    "Impressions": 0.0,
    "Clicks": 0.0,
    "Cost": 0.0,
    "Conversions": 0.0,
    "CTR": "0",
    "CostPerConv": 0.0
  },
  {
    "Campaign": "ULP_PGs_Display",
    "Status": "PAUSED",
    "Budget": 12.5,
    "Impressions": 0.0,
    "Clicks": 0.0,
    "Cost": 0.0,
    "Conversions": 0.0,
    "CTR": "0",
    "CostPerConv": 0.0
  },
  {
    "Campaign": "ULHT_Brasil_Display_Remarketing",
    "Status": "PAUSED",
    "Budget": 37.0,
    "Impressions": 0.0,
    "Clicks": 0.0,
    "Cost": 0.0,
    "Conversions": 0.0,
    "CTR": "0",
    "CostPerConv": 0.0
  },
  {
    "Campaign": "ULP_PG's_Search",
    "Status": "PAUSED",
    "Budget": 14.0,
    "Impressions": 0.0,
    "Clicks": 0.0,
    "Cost": 0.0,
    "Conversions": 0.0,
    "CTR": "0",
    "CostPerConv": 0.0
  },
  {
    "Campaign": "ULP_Licenciaturas_Search SEMANAS AGOSTO",
    "Status": "PAUSED",
    "Budget": 285.0,
    "Impressions": 0.0,
    "Clicks": 0.0,
    "Cost": 0.0,
    "Conversions": 0.0,
    "CTR": "0",
    "CostPerConv": 0.0
  },
  {
    "Campaign": "ULHT_Brasil_Geral",
    "Status": "PAUSED",
    "Budget": 57.24,
    "Impressions": 0.0,
    "Clicks": 0.0,
    "Cost": 0.0,
    "Conversions": 0.0,
    "CTR": "0",
    "CostPerConv": 0.0
  },
  {
    "Campaign": "ULHT_Maiores 23",
    "Status": "PAUSED",
    "Budget": 8.0,
    "Impressions": 0.0,
    "Clicks": 0.0,
    "Cost": 0.0,
    "Conversions": 0.0,
    "CTR": "0",
    "CostPerConv": 0.0
  },
  {
    "Campaign": "ULP_Maiores 23",
    "Status": "PAUSED",
    "Budget": 4.0,
    "Impressions": 0.0,
    "Clicks": 0.0,
    "Cost": 0.0,
    "Conversions": 0.0,
    "CTR": "0",
    "CostPerConv": 0.0
  },
  {
    "Campaign": "ULP_Brasil_Geral",
    "Status": "PAUSED",
    "Budget": 50.0,
    "Impressions": 0.0,
    "Clicks": 0.0,
    "Cost": 0.0,
    "Conversions": 0.0,
    "CTR": "0",
    "CostPerConv": 0.0
  },
  {
    "Campaign": "ULHT_Brasil_Doutoramentos",
    "Status": "PAUSED",
    "Budget": 54.8,
    "Impressions": 0.0,
    "Clicks": 0.0,
    "Cost": 0.0,
    "Conversions": 0.0,
    "CTR": "0",
    "CostPerConv": 0.0
  },
  {
    "Campaign": "ULHT_Brasil_Mestrados",
    "Status": "PAUSED",
    "Budget": 82.0,
    "Impressions": 0.0,
    "Clicks": 0.0,
    "Cost": 0.0,
    "Conversions": 0.0,
    "CTR": "0",
    "CostPerConv": 0.0
  },
  {
    "Campaign": "ULP_Brasil_Licenciaturas",
    "Status": "PAUSED",
    "Budget": 42.0,
    "Impressions": 0.0,
    "Clicks": 0.0,
    "Cost": 0.0,
    "Conversions": 0.0,
    "CTR": "0",
    "CostPerConv": 0.0
  },
  {
    "Campaign": "ULP_Brasil_Mestrados",
    "Status": "PAUSED",
    "Budget": 24.0,
    "Impressions": 0.0,
    "Clicks": 0.0,
    "Cost": 0.0,
    "Conversions": 0.0,
    "CTR": "0",
    "CostPerConv": 0.0
  },
  {
    "Campaign": "ULP_Brasil_Doutoramentos",
    "Status": "PAUSED",
    "Budget": 8.0,
    "Impressions": 0.0,
    "Clicks": 0.0,
    "Cost": 0.0,
    "Conversions": 0.0,
    "CTR": "0",
    "CostPerConv": 0.0
  },
  {
    "Campaign": "ULP_Brasil_Display_Geral_Remarketing",
    "Status": "PAUSED",
    "Budget": 2.0,
    "Impressions": 0.0,
    "Clicks": 0.0,
    "Cost": 0.0,
    "Conversions": 0.0,
    "CTR": "0",
    "CostPerConv": 0.0
  },
  {
    "Campaign": "ULP_Alunos Externos",
    "Status": "PAUSED",
    "Budget": 3.0,
    "Impressions": 0.0,
    "Clicks": 0.0,
    "Cost": 0.0,
    "Conversions": 0.0,
    "CTR": "0",
    "CostPerConv": 0.0
  },
  {
    "Campaign": "ULP_Acesso Técnico Profissional",
    "Status": "PAUSED",
    "Budget": 4.0,
    "Impressions": 0.0,
    "Clicks": 0.0,
    "Cost": 0.0,
    "Conversions": 0.0,
    "CTR": "0",
    "CostPerConv": 0.0
  },
  {
    "Campaign": "ULHT_Alunos Externos",
    "Status": "PAUSED",
    "Budget": 4.0,
    "Impressions": 0.0,
    "Clicks": 0.0,
    "Cost": 0.0,
    "Conversions": 0.0,
    "CTR": "0",
    "CostPerConv": 0.0
  },
  {
    "Campaign": "ULHT_Transferências",
    "Status": "PAUSED",
    "Budget": 4.0,
    "Impressions": 0.0,
    "Clicks": 0.0,
    "Cost": 0.0,
    "Conversions": 0.0,
    "CTR": "0",
    "CostPerConv": 0.0
  },
  {
    "Campaign": "ULP_Transferências",
    "Status": "PAUSED",
    "Budget": 4.0,
    "Impressions": 0.0,
    "Clicks": 0.0,
    "Cost": 0.0,
    "Conversions": 0.0,
    "CTR": "0",
    "CostPerConv": 0.0
  },
  {
    "Campaign": "ULHT_Acesso Técnico Profissional",
    "Status": "PAUSED",
    "Budget": 4.0,
    "Impressions": 0.0,
    "Clicks": 0.0,
    "Cost": 0.0,
    "Conversions": 0.0,
    "CTR": "0",
    "CostPerConv": 0.0
  },
  {
    "Campaign": "Brasil_Geral_CUL_CUP",
    "Status": "PAUSED",
    "Budget": 97.0,
    "Impressions": 0.0,
    "Clicks": 0.0,
    "Cost": 0.0,
    "Conversions": 0.0,
    "CTR": "0",
    "CostPerConv": 0.0
  },
  {
    "Campaign": "CUP CUL_Brasil_Display_Remarketing",
    "Status": "PAUSED",
    "Budget": 16.0,
    "Impressions": 0.0,
    "Clicks": 0.0,
    "Cost": 0.0,
    "Conversions": 0.0,
    "CTR": "0",
    "CostPerConv": 0.0
  },
  {
    "Campaign": "Brasil_Geral_CUL_CUP Experiência - Brasil",
    "Status": "ENABLED",
    "Budget": 97.0,
    "Impressions": 0.0,
    "Clicks": 0.0,
    "Cost": 0.0,
    "Conversions": 0.0,
    "CTR": "0",
    "CostPerConv": 0.0
  },
  {
    "Campaign": "Brasil_Geral_CUL_CUP 2",
    "Status": "ENABLED",
    "Budget": 97.0,
    "Impressions": 0.0,
    "Clicks": 0.0,
    "Cost": 0.0,
    "Conversions": 0.0,
    "CTR": "0",
    "CostPerConv": 0.0
  },
  {
    "Campaign": "CUL - PRR",
    "Status": "PAUSED",
    "Budget": 16.0,
    "Impressions": 0.0,
    "Clicks": 0.0,
    "Cost": 0.0,
    "Conversions": 0.0,
    "CTR": "0",
    "CostPerConv": 0.0
  },
  {
    "Campaign": "ULHT_Licenciaturas Experiências",
    "Status": "ENABLED",
    "Budget": 208.0,
    "Impressions": 0.0,
    "Clicks": 0.0,
    "Cost": 0.0,
    "Conversions": 0.0,
    "CTR": "0",
    "CostPerConv": 0.0
  },
  {
    "Campaign": "Filmeu - Cinema - Finlândia",
    "Status": "PAUSED",
    "Budget": 2.2,
    "Impressions": 0.0,
    "Clicks": 0.0,
    "Cost": 0.0,
    "Conversions": 0.0,
    "CTR": "0",
    "CostPerConv": 0.0
  },
  {
    "Campaign": "Filmeu - Cinema - Suécia",
    "Status": "PAUSED",
    "Budget": 2.2,
    "Impressions": 0.0,
    "Clicks": 0.0,
    "Cost": 0.0,
    "Conversions": 0.0,
    "CTR": "0",
    "CostPerConv": 0.0
  },
  {
    "Campaign": "Cinema - Portugal",
    "Status": "PAUSED",
    "Budget": 2.8,
    "Impressions": 0.0,
    "Clicks": 0.0,
    "Cost": 0.0,
    "Conversions": 0.0,
    "CTR": "0",
    "CostPerConv": 0.0
  },
  {
    "Campaign": "Filmeu - USA",
    "Status": "PAUSED",
    "Budget": 2.2,
    "Impressions": 0.0,
    "Clicks": 0.0,
    "Cost": 0.0,
    "Conversions": 0.0,
    "CTR": "0",
    "CostPerConv": 0.0
  },
  {
    "Campaign": "Cinema - França",
    "Status": "PAUSED",
    "Budget": 2.8,
    "Impressions": 0.0,
    "Clicks": 0.0,
    "Cost": 0.0,
    "Conversions": 0.0,
    "CTR": "0",
    "CostPerConv": 0.0
  },
  {
    "Campaign": "Filmeu - Hungria",
    "Status": "PAUSED",
    "Budget": 2.8,
    "Impressions": 0.0,
    "Clicks": 0.0,
    "Cost": 0.0,
    "Conversions": 0.0,
    "CTR": "0",
    "CostPerConv": 0.0
  },
  {
    "Campaign": "Filmeu - Rep. Checa",
    "Status": "PAUSED",
    "Budget": 2.8,
    "Impressions": 0.0,
    "Clicks": 0.0,
    "Cost": 0.0,
    "Conversions": 0.0,
    "CTR": "0",
    "CostPerConv": 0.0
  },
  {
    "Campaign": "Cinema - Holanda",
    "Status": "PAUSED",
    "Budget": 2.8,
    "Impressions": 0.0,
    "Clicks": 0.0,
    "Cost": 0.0,
    "Conversions": 0.0,
    "CTR": "0",
    "CostPerConv": 0.0
  },
  {
    "Campaign": "Filmeu - Cinema - Noruega",
    "Status": "PAUSED",
    "Budget": 2.2,
    "Impressions": 0.0,
    "Clicks": 0.0,
    "Cost": 0.0,
    "Conversions": 0.0,
    "CTR": "0",
    "CostPerConv": 0.0
  },
  {
    "Campaign": "Cinema - Dinamarca",
    "Status": "PAUSED",
    "Budget": 2.8,
    "Impressions": 0.0,
    "Clicks": 0.0,
    "Cost": 0.0,
    "Conversions": 0.0,
    "CTR": "0",
    "CostPerConv": 0.0
  },
  {
    "Campaign": "Cinema - Irlanda",
    "Status": "PAUSED",
    "Budget": 2.8,
    "Impressions": 0.0,
    "Clicks": 0.0,
    "Cost": 0.0,
    "Conversions": 0.0,
    "CTR": "0",
    "CostPerConv": 0.0
  },
  {
    "Campaign": "Cinema - Reino Unido",
    "Status": "PAUSED",
    "Budget": 2.8,
    "Impressions": 0.0,
    "Clicks": 0.0,
    "Cost": 0.0,
    "Conversions": 0.0,
    "CTR": "0",
    "CostPerConv": 0.0
  },
  {
    "Campaign": "Cinema - Alemanha",
    "Status": "PAUSED",
    "Budget": 2.8,
    "Impressions": 0.0,
    "Clicks": 0.0,
    "Cost": 0.0,
    "Conversions": 0.0,
    "CTR": "0",
    "CostPerConv": 0.0
  },
  {
    "Campaign": "Cinema - Bélgica",
    "Status": "PAUSED",
    "Budget": 2.8,
    "Impressions": 0.0,
    "Clicks": 0.0,
    "Cost": 0.0,
    "Conversions": 0.0,
    "CTR": "0",
    "CostPerConv": 0.0
  },
  {
    "Campaign": "Cinema - Itália",
    "Status": "PAUSED",
    "Budget": 2.8,
    "Impressions": 0.0,
    "Clicks": 0.0,
    "Cost": 0.0,
    "Conversions": 0.0,
    "CTR": "0",
    "CostPerConv": 0.0
  },
  {
    "Campaign": "Cinema - Islândia",
    "Status": "PAUSED",
    "Budget": 2.8,
    "Impressions": 0.0,
    "Clicks": 0.0,
    "Cost": 0.0,
    "Conversions": 0.0,
    "CTR": "0",
    "CostPerConv": 0.0
  },
  {
    "Campaign": "ULHT_Doutoramentos [Experiência _ Correspondência ampla]",
    "Status": "ENABLED",
    "Budget": 25.0,
    "Impressions": 0.0,
    "Clicks": 0.0,
    "Cost": 0.0,
    "Conversions": 0.0,
    "CTR": "0",
    "CostPerConv": 0.0
  },
  {
    "Campaign": "Filmeu - Netherland",
    "Status": "PAUSED",
    "Budget": 2.2,
    "Impressions": 0.0,
    "Clicks": 0.0,
    "Cost": 0.0,
    "Conversions": 0.0,
    "CTR": "0",
    "CostPerConv": 0.0
  },
  {
    "Campaign": "Filmeu - South Africa",
    "Status": "PAUSED",
    "Budget": 2.2,
    "Impressions": 0.0,
    "Clicks": 0.0,
    "Cost": 0.0,
    "Conversions": 0.0,
    "CTR": "0",
    "CostPerConv": 0.0
  },
  {
    "Campaign": "Filmeu - Serbia",
    "Status": "PAUSED",
    "Budget": 2.2,
    "Impressions": 0.0,
    "Clicks": 0.0,
    "Cost": 0.0,
    "Conversions": 0.0,
    "CTR": "0",
    "CostPerConv": 0.0
  },
  {
    "Campaign": "Filmeu - Poland",
    "Status": "PAUSED",
    "Budget": 2.2,
    "Impressions": 0.0,
    "Clicks": 0.0,
    "Cost": 0.0,
    "Conversions": 0.0,
    "CTR": "0",
    "CostPerConv": 0.0
  },
  {
    "Campaign": "Filmeu - Turkey",
    "Status": "PAUSED",
    "Budget": 2.2,
    "Impressions": 0.0,
    "Clicks": 0.0,
    "Cost": 0.0,
    "Conversions": 0.0,
    "CTR": "0",
    "CostPerConv": 0.0
  },
  {
    "Campaign": "Africa_Geral_CUL_CUP",
    "Status": "PAUSED",
    "Budget": 77.0,
    "Impressions": 0.0,
    "Clicks": 0.0,
    "Cost": 0.0,
    "Conversions": 0.0,
    "CTR": "0",
    "CostPerConv": 0.0
  },
  {
    "Campaign": "IPLUSO_Search",
    "Status": "ENABLED",
    "Budget": 16.0,
    "Impressions": 4482.0,
    "Clicks": 1423.0,
    "Cost": 124.883175,
    "Conversions": 10.0,
    "CTR": "0,31749",
    "CostPerConv": 12.4883175
  },
  {
    "Campaign": "IPLUSO_CTesP_Search",
    "Status": "ENABLED",
    "Budget": 41.0,
    "Impressions": 3936.0,
    "Clicks": 396.0,
    "Cost": 500.977017,
    "Conversions": 3.0,
    "CTR": "0,10061",
    "CostPerConv": 166.992339
  },
  {
    "Campaign": "IPLUSO_Licenciaturas_Search",
    "Status": "ENABLED",
    "Budget": 58.0,
    "Impressions": 8991.0,
    "Clicks": 674.0,
    "Cost": 685.828902,
    "Conversions": 4.0,
    "CTR": "0,07496",
    "CostPerConv": 171.4572255
  },
  {
    "Campaign": "IPLUSO_Mestrados_Search",
    "Status": "ENABLED",
    "Budget": 16.0,
    "Impressions": 3216.0,
    "Clicks": 195.0,
    "Cost": 193.309203,
    "Conversions": 0.0,
    "CTR": "0,06063",
    "CostPerConv": 0.0
  },
  {
    "Campaign": "DIsplay IPLUSO Notoriedade",
    "Status": "ENABLED",
    "Budget": 6.0,
    "Impressions": 0.0,
    "Clicks": 0.0,
    "Cost": 0.0,
    "Conversions": 0.0,
    "CTR": "0",
    "CostPerConv": 0.0
  },
  {
    "Campaign": "Display IPLUSO Posicionamento CTeSPs/Lics",
    "Status": "ENABLED",
    "Budget": 10.0,
    "Impressions": 0.0,
    "Clicks": 0.0,
    "Cost": 0.0,
    "Conversions": 0.0,
    "CTR": "0",
    "CostPerConv": 0.0
  },
  {
    "Campaign": "IPLUSO_Licenciaturas_AGOSTO",
    "Status": "PAUSED",
    "Budget": 142.0,
    "Impressions": 0.0,
    "Clicks": 0.0,
    "Cost": 0.0,
    "Conversions": 0.0,
    "CTR": "0",
    "CostPerConv": 0.0
  },
  {
    "Campaign": "IPLUSO_Formação_Modulares_Search",
    "Status": "PAUSED",
    "Budget": 28.0,
    "Impressions": 0.0,
    "Clicks": 0.0,
    "Cost": 0.0,
    "Conversions": 0.0,
    "CTR": "0",
    "CostPerConv": 0.0
  },
  {
    "Campaign": "IPLUSO_CTesP_Search_novos_cursos",
    "Status": "PAUSED",
    "Budget": 33.0,
    "Impressions": 0.0,
    "Clicks": 0.0,
    "Cost": 0.0,
    "Conversions": 0.0,
    "CTR": "0",
    "CostPerConv": 0.0
  },
  {
    "Campaign": "IPLUSO_Brasil_Geral",
    "Status": "PAUSED",
    "Budget": 16.0,
    "Impressions": 0.0,
    "Clicks": 0.0,
    "Cost": 0.0,
    "Conversions": 0.0,
    "CTR": "0",
    "CostPerConv": 0.0
  },
  {
    "Campaign": "IPLUSO_Acesso Técnico Profissional",
    "Status": "PAUSED",
    "Budget": 4.0,
    "Impressions": 0.0,
    "Clicks": 0.0,
    "Cost": 0.0,
    "Conversions": 0.0,
    "CTR": "0",
    "CostPerConv": 0.0
  },
  {
    "Campaign": "IPLUSO_Maiores 23",
    "Status": "PAUSED",
    "Budget": 4.0,
    "Impressions": 0.0,
    "Clicks": 0.0,
    "Cost": 0.0,
    "Conversions": 0.0,
    "CTR": "0",
    "CostPerConv": 0.0
  },
  {
    "Campaign": "ISMAT_Geral_Search",
    "Status": "ENABLED",
    "Budget": 20.0,
    "Impressions": 3294.0,
    "Clicks": 956.0,
    "Cost": 203.231523,
    "Conversions": 4.0,
    "CTR": "0,29022",
    "CostPerConv": 50.80788075
  },
  {
    "Campaign": "ISMAT_Mestrados_Search",
    "Status": "ENABLED",
    "Budget": 33.0,
    "Impressions": 4926.0,
    "Clicks": 409.0,
    "Cost": 336.737243,
    "Conversions": 0.0,
    "CTR": "0,08303",
    "CostPerConv": 0.0
  },
  {
    "Campaign": "ISMAT_PG's_Search",
    "Status": "PAUSED",
    "Budget": 6.0,
    "Impressions": 0.0,
    "Clicks": 0.0,
    "Cost": 0.0,
    "Conversions": 0.0,
    "CTR": "0",
    "CostPerConv": 0.0
  },
  {
    "Campaign": "ISMAT_Licenciaturas_Search",
    "Status": "ENABLED",
    "Budget": 58.0,
    "Impressions": 8178.0,
    "Clicks": 535.0,
    "Cost": 616.055314,
    "Conversions": 1.0,
    "CTR": "0,06542",
    "CostPerConv": 616.055314
  },
  {
    "Campaign": "Display Notoriedade",
    "Status": "PAUSED",
    "Budget": 5.0,
    "Impressions": 0.0,
    "Clicks": 0.0,
    "Cost": 0.0,
    "Conversions": 0.0,
    "CTR": "0",
    "CostPerConv": 0.0
  },
  {
    "Campaign": "ISMAT_Licenciaturas_Search_AGOSTO",
    "Status": "PAUSED",
    "Budget": 142.0,
    "Impressions": 0.0,
    "Clicks": 0.0,
    "Cost": 0.0,
    "Conversions": 0.0,
    "CTR": "0",
    "CostPerConv": 0.0
  },
  {
    "Campaign": "ISMAT_Maiores de 23",
    "Status": "PAUSED",
    "Budget": 4.0,
    "Impressions": 0.0,
    "Clicks": 0.0,
    "Cost": 0.0,
    "Conversions": 0.0,
    "CTR": "0",
    "CostPerConv": 0.0
  },
  {
    "Campaign": "ISMAT_Brasil_Geral",
    "Status": "PAUSED",
    "Budget": 16.0,
    "Impressions": 0.0,
    "Clicks": 0.0,
    "Cost": 0.0,
    "Conversions": 0.0,
    "CTR": "0",
    "CostPerConv": 0.0
  },
  {
    "Campaign": "ISMAT_Acesso Técnico Profissional",
    "Status": "PAUSED",
    "Budget": 4.0,
    "Impressions": 0.0,
    "Clicks": 0.0,
    "Cost": 0.0,
    "Conversions": 0.0,
    "CTR": "0",
    "CostPerConv": 0.0
  },
  {
    "Campaign": "ISLA GAIA_CTeSP_Search",
    "Status": "ENABLED",
    "Budget": 41.0,
    "Impressions": 1731.0,
    "Clicks": 145.0,
    "Cost": 379.17384,
    "Conversions": 0.0,
    "CTR": "0,08377",
    "CostPerConv": 0.0
  },
  {
    "Campaign": "ISLA GAIA_Licenciaturas_Search",
    "Status": "ENABLED",
    "Budget": 58.0,
    "Impressions": 4541.0,
    "Clicks": 282.0,
    "Cost": 545.717433,
    "Conversions": 0.0,
    "CTR": "0,0621",
    "CostPerConv": 0.0
  },
  {
    "Campaign": "ISLA GAIA_Mestrados",
    "Status": "ENABLED",
    "Budget": 41.0,
    "Impressions": 2710.0,
    "Clicks": 142.0,
    "Cost": 383.008817,
    "Conversions": 0.0,
    "CTR": "0,0524",
    "CostPerConv": 0.0
  },
  {
    "Campaign": "Display ISLAGAIA Notoriedade",
    "Status": "ENABLED",
    "Budget": 5.0,
    "Impressions": 0.0,
    "Clicks": 0.0,
    "Cost": 0.0,
    "Conversions": 0.0,
    "CTR": "0",
    "CostPerConv": 0.0
  },
  {
    "Campaign": "ISLA GAIA_Maiores de 23",
    "Status": "PAUSED",
    "Budget": 4.0,
    "Impressions": 0.0,
    "Clicks": 0.0,
    "Cost": 0.0,
    "Conversions": 0.0,
    "CTR": "0",
    "CostPerConv": 0.0
  },
  {
    "Campaign": "ISLA GAIA_Geral",
    "Status": "ENABLED",
    "Budget": 16.0,
    "Impressions": 2038.0,
    "Clicks": 717.0,
    "Cost": 145.759188,
    "Conversions": 3.0,
    "CTR": "0,35182",
    "CostPerConv": 48.586396
  },
  {
    "Campaign": "ISLA GAIA_Brasil_Geral",
    "Status": "PAUSED",
    "Budget": 16.0,
    "Impressions": 0.0,
    "Clicks": 0.0,
    "Cost": 0.0,
    "Conversions": 0.0,
    "CTR": "0",
    "CostPerConv": 0.0
  },
  {
    "Campaign": "ISLA_GAIA_ Acesso Técnico Profissional",
    "Status": "PAUSED",
    "Budget": 4.0,
    "Impressions": 0.0,
    "Clicks": 0.0,
    "Cost": 0.0,
    "Conversions": 0.0,
    "CTR": "0",
    "CostPerConv": 0.0
  },
  {
    "Campaign": "ISLA GAIA_CTeSP_Search Máx Cliques ou Conversões?",
    "Status": "ENABLED",
    "Budget": 41.0,
    "Impressions": 0.0,
    "Clicks": 0.0,
    "Cost": 0.0,
    "Conversions": 0.0,
    "CTR": "0",
    "CostPerConv": 0.0
  },
  {
    "Campaign": "ISLA GAIA_Licenciaturas_Search GAIA_Licenciaturas_Search_Experiência",
    "Status": "ENABLED",
    "Budget": 58.0,
    "Impressions": 0.0,
    "Clicks": 0.0,
    "Cost": 0.0,
    "Conversions": 0.0,
    "CTR": "0",
    "CostPerConv": 0.0
  },
  {
    "Campaign": "ISLA GAIA_Pós-graduações_Search",
    "Status": "PAUSED",
    "Budget": 26.0,
    "Impressions": 0.0,
    "Clicks": 0.0,
    "Cost": 0.0,
    "Conversions": 0.0,
    "CTR": "0",
    "CostPerConv": 0.0
  }
]